odoo/addons/website_event_crm/README.rst
odoo/addons/website_event_crm/__init__.py
odoo/addons/website_event_crm/__manifest__.py
odoo/addons/website_event_crm/data/ir_cron_data.xml
odoo/addons/website_event_crm/data/mail_template_data.xml
odoo/addons/website_event_crm/i18n/es.po
odoo/addons/website_event_crm/i18n/website_event_crm.pot
odoo/addons/website_event_crm/models/__init__.py
odoo/addons/website_event_crm/models/crm_lead.py
odoo/addons/website_event_crm/models/crm_stage.py
odoo/addons/website_event_crm/models/event_type.py
odoo/addons/website_event_crm/readme/CONFIGURE.rst
odoo/addons/website_event_crm/readme/CONTRIBUTORS.rst
odoo/addons/website_event_crm/readme/DESCRIPTION.rst
odoo/addons/website_event_crm/readme/INSTALL.rst
odoo/addons/website_event_crm/readme/USAGE.rst
odoo/addons/website_event_crm/static/description/icon.png
odoo/addons/website_event_crm/static/description/index.html
odoo/addons/website_event_crm/tests/__init__.py
odoo/addons/website_event_crm/tests/test_website_event_crm.py
odoo/addons/website_event_crm/views/crm_lead_view.xml
odoo/addons/website_event_crm/views/crm_stage_view.xml
odoo/addons/website_event_crm/wizards/__init__.py
odoo/addons/website_event_crm/wizards/mail_compose_message.py
odoo13_addon_website_event_crm-13.0.1.1.1.dist-info/METADATA
odoo13_addon_website_event_crm-13.0.1.1.1.dist-info/WHEEL
odoo13_addon_website_event_crm-13.0.1.1.1.dist-info/top_level.txt
odoo13_addon_website_event_crm-13.0.1.1.1.dist-info/RECORD
